src/ALU.v
module ALU (
    input wire [2:0] S,        // 3-bit Operation selector or Opcode
    input wire [3:0] A, B,     // 4-bit Operands A and B
    output reg [3:0] F,        // 4-bit Result Output
    output wire Z,             // Zero Flag
    output reg C               // Carry Flag
);

    reg [4:0] sum;             // 5-bit temporary result for Addition and Substraction
    assign Z = (F == 4'b0000); // Zero Flag asserted When F is zero

    always @(*) begin          
        C = 0;
        F = 4'b0;
        sum = 5'b0;

        case (S)
            3'b000: F = 4'b0000;
            3'b001: begin
                sum = A + B;      // Addition
                F = sum[3:0];     // Output Result in 4-bit
                C = sum[4];       // Carry Flag ( 1 means carry occured)
            end
            3'b010: begin
                sum = {1'b0, A} - {1'b0, B};      // Subtraction
                F = sum[3:0];                     // Output Result in 4-bit
                C = ~sum[4];                      // Carry Flag = Borrow Flag (0 menas borrow occured)
            end
            3'b011: F = A | B;                    // OR
            3'b100: F = A & B;                    // AND
            3'b101: F = A ^ B;                    // XOR
            3'b110: begin
                F = A << 1;                       // Left Shift
                C = A[3];                         // Carry Flag = the shifted out bit
            end
            3'b111: begin
                F = A >> 1;                       // Right Shift
                C = A[0];                         // Carry Flag  = the shifted out bit
            end
            default: begin 
                F = 4'b1111;
                C = 0;
            end
        endcase

    end

endmodule

src/ALU_tb.v
`timescale 1ns / 1ps

module ALU_tb();

    reg [2:0] S;
    reg [3:0] A, B;
    wire [3:0] F;
    wire Z, C;

    task alu;
        input [2:0] op;
        input [3:0] a, b;
        input [32*8:1] string;
        begin
            S = op; A = a; B = b; #10;
            $display("\nOpcode : %b (%0s)\n", op, string);
            $display("  A = %4b : B = %4b : F_bin = %4b : F = %0d : C = %b : Z = %b \n", a, b, F, F, C, Z);
        end
    endtask

    initial begin
        $dumpfile("ALU_wave.vcd");  // Output file for waveform
        $dumpvars(0, ALU_tb);       // Dumps all signals in this testbench

        // Clear
        alu(3'b000, 4'b0000, 4'b0000, "Clear");

        // Addition
        alu(3'b001, 4'b1001, 4'b0111, "Addition_1 (9 + 7)");  // Addition test with carry bit
        alu(3'b001, 4'b0011, 4'b0101, "Addition_2 (3 + 5)");  // Normal addition within 4-bit
        alu(3'b001, 4'b0000, 4'b0000, "Addition_3 (0 + 0)");  // 0 + 0 = 0 ; zero flag

        // Subtraction
        alu(3'b010, 4'b1010, 4'b0101, "Subtraction_1 (10 - 5)"); // Normal Addition within 4-bit
        alu(3'b010, 4'b0111, 4'b0111, "Subtraction_2 (7 - 7)");  // 7 - 7 = 0 ; zero flag 
        alu(3'b010, 4'b0000, 4'b0001, "Subtraction_3 (0 - 1)");  // Tests borrow Flag and negative result handling
        alu(3'b010, 4'b0010, 4'b0100, "Subtraction_4 (2 - 4)");  // Tests borrow flag and negative result handling

        // OR 
        alu(3'b011, 4'b1010, 4'b0101, "OR (1010 | 0101)");

        // AND
        alu(3'b100, 4'b1010, 4'b1100, "AND (1010 & 1100)");

        // XOR
        alu(3'b101, 4'b1111, 4'b1010, "XOR (1111 ^ 1010)");

        // Left Shift
        alu(3'b110, 4'b0000, 4'b0000, "Left Shift_1 (0000 << 1)");  // Left shift all zero
        alu(3'b110, 4'b1111, 4'b0000, "Left Shift_2 (1111 << 1)");  // Left shift all one
        alu(3'b110, 4'b1000, 4'b0000, "Left Shift_3 (1000 << 1)");  // Left shift MSB bit

        // Right Shift
        alu(3'b111, 4'b0000, 4'b0000, "Right Shift_1 (0000 >> 1)");  // Right shift all zero
        alu(3'b111, 4'b1111, 4'b0000, "Right Shift_2 (1111 >> 1)");  // Right shift all one
        alu(3'b111, 4'b0001, 4'b0000, "Right Shift_3 (0001 >> 1)");  // Right shift LSB bit

        #10
        $finish;
    end


    // Instances
    ALU ALU_ins (
        .S(S),
        .A(A),
        .B(B),
        .F(F),
        .Z(Z),
        .C(C)
    );

endmodule

sim/ALU_wave.vcd
$date
	Mon Jul 28 22:38:00 2025
$end
$version
	Icarus Verilog
$end
$timescale
	1ps
$end
$scope module ALU_tb $end
$var wire 1 ! Z $end
$var wire 4 " F [3:0] $end
$var wire 1 # C $end
$var reg 4 $ A [3:0] $end
$var reg 4 % B [3:0] $end
$var reg 3 & S [2:0] $end
$scope module ALU_ins $end
$var wire 4 ' A [3:0] $end
$var wire 4 ( B [3:0] $end
$var wire 3 ) S [2:0] $end
$var wire 1 ! Z $end
$var reg 1 # C $end
$var reg 4 * F [3:0] $end
$var reg 5 + sum [4:0] $end
$upscope $end
$scope task alu $end
$var reg 4 , a [3:0] $end
$var reg 4 - b [3:0] $end
$var reg 3 . op [2:0] $end
$var reg 256 / string [256:1] $end
$upscope $end
$upscope $end
$enddefinitions $end
$comment Show the parameter values. $end
$dumpall
$end
#0
$dumpvars
b100001101101100011001010110000101110010 /
b0 .
b0 -
b0 ,
b0 +
b0 *
b0 )
b0 (
b0 '
b0 &
b0 %
b0 $
0#
b0 "
1!
$end
#10000
1#
b10000 +
b111 %
b111 (
b1001 $
b1001 '
b1 &
b1 )
b10000010110010001100100011010010111010001101001011011110110111001011111001100010010000000101000001110010010000000101011001000000011011100101001 /
b111 -
b1001 ,
b1 .
#20000
0!
b1000 "
b1000 *
b1000 +
0#
b101 %
b101 (
b11 $
b11 '
b10000010110010001100100011010010111010001101001011011110110111001011111001100100010000000101000001100110010000000101011001000000011010100101001 /
b101 -
b11 ,
#30000
b0 +
1!
b0 "
b0 *
b0 %
b0 (
b0 $
b0 '
b10000010110010001100100011010010111010001101001011011110110111001011111001100110010000000101000001100000010000000101011001000000011000000101001 /
b0 -
b0 ,
#40000
1#
0!
b101 "
b101 *
b101 +
b101 %
b101 (
b1010 $
b1010 '
b10 &
b10 )
b1010011011101010110001001110100011100100110000101100011011101000110100101101111011011100101111100110001001000000010100000110001001100000010000000101101001000000011010100101001 /
b101 -
b1010 ,
b10 .
#50000
b0 +
1!
b0 "
b0 *
1#
b111 %
b111 (
b111 $
b111 '
b10100110111010101100010011101000111001001100001011000110111010001101001011011110110111001011111001100100010000000101000001101110010000000101101001000000011011100101001 /
b111 -
b111 ,
#60000
0!
b1111 "
b1111 *
b11111 +
0#
b1 %
b1 (
b0 $
b0 '
b10100110111010101100010011101000111001001100001011000110111010001101001011011110110111001011111001100110010000000101000001100000010000000101101001000000011000100101001 /
b1 -
b0 ,
#70000
b11110 +
0!
b1110 "
b1110 *
b100 %
b100 (
b10 $
b10 '
b10100110111010101100010011101000111001001100001011000110111010001101001011011110110111001011111001101000010000000101000001100100010000000101101001000000011010000101001 /
b100 -
b10 ,
#80000
b0 +
0!
b1111 "
b1111 *
b101 %
b101 (
b1010 $
b1010 '
b11 &
b11 )
b1001111010100100010000000101000001100010011000000110001001100000010000001111100001000000011000000110001001100000011000100101001 /
b101 -
b1010 ,
b11 .
#90000
0!
b1000 "
b1000 *
b1100 %
b1100 (
b100 &
b100 )
b100000101001110010001000010000000101000001100010011000000110001001100000010000000100110001000000011000100110001001100000011000000101001 /
b1100 -
b100 .
#100000
0!
b101 "
b101 *
b1010 %
b1010 (
b1111 $
b1111 '
b101 &
b101 )
b101100001001111010100100010000000101000001100010011000100110001001100010010000001011110001000000011000100110000001100010011000000101001 /
b1010 -
b1111 ,
b101 .
#110000
1!
b0 "
b0 *
b0 %
b0 (
b0 $
b0 '
b110 &
b110 )
b10011000110010101100110011101000010000001010011011010000110100101100110011101000101111100110001001000000010100000110000001100000011000000110000001000000011110000111100001000000011000100101001 /
b0 -
b0 ,
b110 .
#120000
1#
0!
b1110 "
b1110 *
b1111 $
b1111 '
b10011000110010101100110011101000010000001010011011010000110100101100110011101000101111100110010001000000010100000110001001100010011000100110001001000000011110000111100001000000011000100101001 /
b1111 ,
#130000
1!
b0 "
b0 *
1#
b1000 $
b1000 '
b10011000110010101100110011101000010000001010011011010000110100101100110011101000101111100110011001000000010100000110001001100000011000000110000001000000011110000111100001000000011000100101001 /
b1000 ,
#140000
0#
b0 $
b0 '
b111 &
b111 )
b1010010011010010110011101101000011101000010000001010011011010000110100101100110011101000101111100110001001000000010100000110000001100000011000000110000001000000011111000111110001000000011000100101001 /
b0 ,
b111 .
#150000
1#
0!
b111 "
b111 *
b1111 $
b1111 '
b1010010011010010110011101101000011101000010000001010011011010000110100101100110011101000101111100110010001000000010100000110001001100010011000100110001001000000011111000111110001000000011000100101001 /
b1111 ,
#160000
1!
b0 "
b0 *
1#
b1 $
b1 '
b1010010011010010110011101101000011101000010000001010011011010000110100101100110011101000101111100110011001000000010100000110000001100000011000000110001001000000011111000111110001000000011000100101001 /
b1 ,
